livechat_webservice/__init__.py
livechat_webservice/client.py
livechat_webservice/config.py
livechat_webservice/logger.py
livechat_webservice-0.1.0.dist-info/licenses/LICENSE
livechat_webservice-0.1.0.dist-info/METADATA
livechat_webservice-0.1.0.dist-info/WHEEL
livechat_webservice-0.1.0.dist-info/top_level.txt
livechat_webservice-0.1.0.dist-info/RECORD
